mkdocs_fix_github_wiki_url_plugin/__init__.py
mkdocs_fix_github_wiki_url_plugin/plugin.py
mkdocs_fix_github_wiki_url_plugin-0.1.22.dist-info/LICENSE
mkdocs_fix_github_wiki_url_plugin-0.1.22.dist-info/METADATA
mkdocs_fix_github_wiki_url_plugin-0.1.22.dist-info/WHEEL
mkdocs_fix_github_wiki_url_plugin-0.1.22.dist-info/entry_points.txt
mkdocs_fix_github_wiki_url_plugin-0.1.22.dist-info/top_level.txt
mkdocs_fix_github_wiki_url_plugin-0.1.22.dist-info/RECORD
