Metadata-Version: 2.1
Name: mkdocs-fix-github-wiki-url-plugin
Version: 0.1.22
Summary: UNKNOWN
Home-page: https://github.com/xiaoxiao921/mkdocs-fix-github-wiki-url-plugin
Author: Quentin Escarbajal
Author-email: xiaoxiao921@hotmail.fr
License: MIT
Platform: UNKNOWN
Requires-Python: >=3.6
License-File: LICENSE
Requires-Dist: mkdocs (<2,>=1.1.0)
